{
  "list": {
    "code": "10000",
    "message": "success",
    "result": {
      "haveNext": 1,
      "nextPage": 2,
      "havePre": 0,
      "prePage": 1,
      "currentPage": 1,
      "count": 874,
      "sumPage": 59,
      "pageSize": 15,
      "dataList": [
        {
          "audioId": 1000001078282,
          "audioName": "【凯叔讲故事】268. 爱音乐的马克",
          "audioPic": "http://img.kaolafm.net/mz/images/201505/4c4bade5-a248-4736-a29c-aaa2589ccd04/default.jpg",
          "audioDes": "优质儿童故事自媒体平台。由著名主持人，两个女儿的父亲光头王凯创立。两天一次优质儿童绘本故事推送，每天一篇经典育儿文章推荐，更多互动活动为宝贝提供展示平台，帮助宝贝塑造健康的人格，和孩子一起成长。",
          "albumId": 1100000050295,
          "albumPic": "http://img.kaolafm.net/mz/images/201603/00553b48-49cd-4188-acf0-b979610214d4/default.png",
          "albumName": "凯叔讲故事",
          "orderNum": 1,
          "playUrl": "http://image.kaolafm.net/mz/outopus_16/201506/21406f5e-db80-491d-a891-571a6477b558.opus",
          "mp3PlayUrl": "http://image.kaolafm.net/mz/audios/201506/21406f5e-db80-491d-a891-571a6477b558.mp3",
          "aacPlayUrl": "http://image.kaolafm.net/mz/aac_64/201506/21406f5e-db80-491d-a891-571a6477b558.aac",
          "m3u8PlayUrl": "http://image.kaolafm.net/mz/aac_64/201506/21406f5e-db80-491d-a891-571a6477b558/playlist.m3u8",
          "shareUrl": "http://m.kaolafm.com/share/jm.html?audioId=1000001078282",
          "categoryId": 125,
          "host": [],
          "fileSize": 4708130,
          "aacFileSize": 4769421,
          "mp3FileSize": 23550125,
          "isStored": 0,
          "updateTime": "2015-06-10",
          "createTime": 1433896016000,
          "clockId": "",
          "duration": 588000,
          "originalDuration": 599721,
          "mp3Duration": 588000,
          "listenNum": 121069,
          "likedNum": 243,
          "islistened": 0,
          "hasCopyright": 1,
          "type": 1,
          "tips": "",
          "commentNum": 20,
          "uploaderId": 2102332,
          "uploaderName": "凯叔讲故事",
          "uploaderImg": "http://img.kaolafm.net/mz/images/201511/52fd524c-7ca3-4158-8d37-c532eac187ee/default.jpg",
          "isReward": 0,
          "trailerStart": 0,
          "trailerEnd": 0
        },
        {
          "audioId": 1000001078283,
          "audioName": "【凯叔讲故事】269. 我不知道我是谁",
          "audioPic": "http://img.kaolafm.net/mz/images/201505/4c4bade5-a248-4736-a29c-aaa2589ccd04/default.jpg",
          "audioDes": "优质儿童故事自媒体平台。由著名主持人，两个女儿的父亲光头王凯创立。两天一次优质儿童绘本故事推送，每天一篇经典育儿文章推荐，更多互动活动为宝贝提供展示平台，帮助宝贝塑造健康的人格，和孩子一起成长。",
          "albumId": 1100000050295,
          "albumPic": "http://img.kaolafm.net/mz/images/201603/00553b48-49cd-4188-acf0-b979610214d4/default.png",
          "albumName": "凯叔讲故事",
          "orderNum": 2,
          "playUrl": "http://image.kaolafm.net/mz/outopus_16/201506/4af3c602-f538-4d54-b22b-3b83838c6f48.opus",
          "mp3PlayUrl": "http://image.kaolafm.net/mz/audios/201506/4af3c602-f538-4d54-b22b-3b83838c6f48.mp3",
          "aacPlayUrl": "http://image.kaolafm.net/mz/aac_64/201506/4af3c602-f538-4d54-b22b-3b83838c6f48.aac",
          "m3u8PlayUrl": "http://image.kaolafm.net/mz/aac_64/201506/4af3c602-f538-4d54-b22b-3b83838c6f48/playlist.m3u8",
          "shareUrl": "http://m.kaolafm.com/share/jm.html?audioId=1000001078283",
          "categoryId": 125,
          "host": [],
          "fileSize": 2380787,
          "aacFileSize": 4761885,
          "mp3FileSize": 23480120,
          "isStored": 0,
          "updateTime": "2015-06-10",
          "createTime": 1433896389000,
          "clockId": "",
          "duration": 587052,
          "originalDuration": 597002,
          "mp3Duration": 597002,
          "listenNum": 96678,
          "likedNum": 88,
          "islistened": 0,
          "hasCopyright": 1,
          "type": 1,
          "tips": "",
          "commentNum": 15,
          "uploaderId": 2102332,
          "uploaderName": "凯叔讲故事",
          "uploaderImg": "http://img.kaolafm.net/mz/images/201511/52fd524c-7ca3-4158-8d37-c532eac187ee/default.jpg",
          "isReward": 0,
          "trailerStart": 0,
          "trailerEnd": 0
        },
        {
          "audioId": 1000001078284,
          "audioName": "【凯叔睡前诗】忆江南",
          "audioPic": "http://img.kaolafm.net/mz/images/201505/4c4bade5-a248-4736-a29c-aaa2589ccd04/default.jpg",
          "audioDes": "优质儿童故事自媒体平台。由著名主持人，两个女儿的父亲光头王凯创立。两天一次优质儿童绘本故事推送，每天一篇经典育儿文章推荐，更多互动活动为宝贝提供展示平台，帮助宝贝塑造健康的人格，和孩子一起成长。",
          "albumId": 1100000050295,
          "albumPic": "http://img.kaolafm.net/mz/images/201603/00553b48-49cd-4188-acf0-b979610214d4/default.png",
          "albumName": "凯叔讲故事",
          "orderNum": 3,
          "playUrl": "http://image.kaolafm.net/mz/outopus_16/201506/ff5d8e6f-43b6-4c59-ab72-351fe668e176.opus",
          "mp3PlayUrl": "http://image.kaolafm.net/mz/audios/201506/ff5d8e6f-43b6-4c59-ab72-351fe668e176.mp3",
          "aacPlayUrl": "http://image.kaolafm.net/mz/aac_64/201506/ff5d8e6f-43b6-4c59-ab72-351fe668e176.aac",
          "m3u8PlayUrl": "http://image.kaolafm.net/mz/aac_64/201506/ff5d8e6f-43b6-4c59-ab72-351fe668e176/playlist.m3u8",
          "shareUrl": "http://m.kaolafm.com/share/jm.html?audioId=1000001078284",
          "categoryId": 125,
          "host": [],
          "fileSize": 1650464,
          "aacFileSize": 1650464,
          "mp3FileSize": 8253850,
          "isStored": 0,
          "updateTime": "2015-06-10",
          "createTime": 1433896430000,
          "clockId": "",
          "duration": 206236,
          "originalDuration": 206315,
          "mp3Duration": 206315,
          "listenNum": 88202,
          "likedNum": 20,
          "islistened": 0,
          "hasCopyright": 1,
          "type": 1,
          "tips": "",
          "commentNum": 7,
          "uploaderId": 2102332,
          "uploaderName": "凯叔讲故事",
          "uploaderImg": "http://img.kaolafm.net/mz/images/201511/52fd524c-7ca3-4158-8d37-c532eac187ee/default.jpg",
          "isReward": 0,
          "trailerStart": 0,
          "trailerEnd": 0
        },
        {
          "audioId": 1000001078285,
          "audioName": "【凯叔讲故事】272. 那只深蓝色的鸟是我爸爸",
          "audioPic": "http://img.kaolafm.net/mz/images/201505/4c4bade5-a248-4736-a29c-aaa2589ccd04/default.jpg",
          "audioDes": "优质儿童故事自媒体平台。由著名主持人，两个女儿的父亲光头王凯创立。两天一次优质儿童绘本故事推送，每天一篇经典育儿文章推荐，更多互动活动为宝贝提供展示平台，帮助宝贝塑造健康的人格，和孩子一起成长。",
          "albumId": 1100000050295,
          "albumPic": "http://img.kaolafm.net/mz/images/201603/00553b48-49cd-4188-acf0-b979610214d4/default.png",
          "albumName": "凯叔讲故事",
          "orderNum": 4,
          "playUrl": "http://image.kaolafm.net/mz/outopus_16/201506/17c04ccd-fef0-4170-b94c-51a4db9fa242.opus",
          "mp3PlayUrl": "http://image.kaolafm.net/mz/audios/201506/17c04ccd-fef0-4170-b94c-51a4db9fa242.mp3",
          "aacPlayUrl": "http://image.kaolafm.net/mz/aac_64/201506/17c04ccd-fef0-4170-b94c-51a4db9fa242.aac",
          "m3u8PlayUrl": "http://image.kaolafm.net/mz/aac_64/201506/17c04ccd-fef0-4170-b94c-51a4db9fa242/playlist.m3u8",
          "shareUrl": "http://m.kaolafm.com/share/jm.html?audioId=1000001078285",
          "categoryId": 125,
          "host": [],
          "fileSize": 2225765,
          "aacFileSize": 4452084,
          "mp3FileSize": 21778791,
          "isStored": 0,
          "updateTime": "2015-06-10",
          "createTime": 1433896432000,
          "clockId": "",
          "duration": 544500,
          "originalDuration": 556907,
          "mp3Duration": 556907,
          "listenNum": 83914,
          "likedNum": 36,
          "islistened": 0,
          "hasCopyright": 1,
          "type": 1,
          "tips": "",
          "commentNum": 10,
          "uploaderId": 2102332,
          "uploaderName": "凯叔讲故事",
          "uploaderImg": "http://img.kaolafm.net/mz/images/201511/52fd524c-7ca3-4158-8d37-c532eac187ee/default.jpg",
          "isReward": 0,
          "trailerStart": 0,
          "trailerEnd": 0
        },
        {
          "audioId": 1000001078286,
          "audioName": "【凯叔睡前诗】纵游淮南",
          "audioPic": "http://img.kaolafm.net/mz/images/201505/4c4bade5-a248-4736-a29c-aaa2589ccd04/default.jpg",
          "audioDes": "优质儿童故事自媒体平台。由著名主持人，两个女儿的父亲光头王凯创立。两天一次优质儿童绘本故事推送，每天一篇经典育儿文章推荐，更多互动活动为宝贝提供展示平台，帮助宝贝塑造健康的人格，和孩子一起成长。",
          "albumId": 1100000050295,
          "albumPic": "http://img.kaolafm.net/mz/images/201603/00553b48-49cd-4188-acf0-b979610214d4/default.png",
          "albumName": "凯叔讲故事",
          "orderNum": 5,
          "playUrl": "http://image.kaolafm.net/mz/outopus_16/201506/83443801-015a-4dac-a4f9-31dfb6aa88f5.opus",
          "mp3PlayUrl": "http://image.kaolafm.net/mz/audios/201506/83443801-015a-4dac-a4f9-31dfb6aa88f5.mp3",
          "aacPlayUrl": "http://image.kaolafm.net/mz/aac_64/201506/83443801-015a-4dac-a4f9-31dfb6aa88f5.aac",
          "m3u8PlayUrl": "http://image.kaolafm.net/mz/aac_64/201506/83443801-015a-4dac-a4f9-31dfb6aa88f5/playlist.m3u8",
          "shareUrl": "http://m.kaolafm.com/share/jm.html?audioId=1000001078286",
          "categoryId": 125,
          "host": [],
          "fileSize": 1295072,
          "aacFileSize": 1295072,
          "mp3FileSize": 6475405,
          "isStored": 0,
          "updateTime": "2015-06-10",
          "createTime": 1433896434000,
          "clockId": "",
          "duration": 161832,
          "originalDuration": 161856,
          "mp3Duration": 161856,
          "listenNum": 73098,
          "likedNum": 13,
          "islistened": 0,
          "hasCopyright": 1,
          "type": 1,
          "tips": "",
          "commentNum": 5,
          "uploaderId": 2102332,
          "uploaderName": "凯叔讲故事",
          "uploaderImg": "http://img.kaolafm.net/mz/images/201511/52fd524c-7ca3-4158-8d37-c532eac187ee/default.jpg",
          "isReward": 0,
          "trailerStart": 0,
          "trailerEnd": 0
        },
        {
          "audioId": 1000001078287,
          "audioName": "【凯叔讲故事】263.灯塔守护人：8.大海里来的新朋友",
          "audioPic": "http://img.kaolafm.net/mz/images/201505/4c4bade5-a248-4736-a29c-aaa2589ccd04/default.jpg",
          "audioDes": "优质儿童故事自媒体平台。由著名主持人，两个女儿的父亲光头王凯创立。两天一次优质儿童绘本故事推送，每天一篇经典育儿文章推荐，更多互动活动为宝贝提供展示平台，帮助宝贝塑造健康的人格，和孩子一起成长。",
          "albumId": 1100000050295,
          "albumPic": "http://img.kaolafm.net/mz/images/201603/00553b48-49cd-4188-acf0-b979610214d4/default.png",
          "albumName": "凯叔讲故事",
          "orderNum": 6,
          "playUrl": "http://image.kaolafm.net/mz/outopus_16/201506/3a7e210b-c956-4b2f-8c2e-a53a6f89e1e9.opus",
          "mp3PlayUrl": "http://image.kaolafm.net/mz/audios/201506/3a7e210b-c956-4b2f-8c2e-a53a6f89e1e9.mp3",
          "aacPlayUrl": "http://image.kaolafm.net/mz/aac_64/201506/3a7e210b-c956-4b2f-8c2e-a53a6f89e1e9.aac",
          "m3u8PlayUrl": "http://image.kaolafm.net/mz/aac_64/201506/3a7e210b-c956-4b2f-8c2e-a53a6f89e1e9/playlist.m3u8",
          "shareUrl": "http://m.kaolafm.com/share/jm.html?audioId=1000001078287",
          "categoryId": 125,
          "host": [],
          "fileSize": 14024524,
          "aacFileSize": 13982618,
          "mp3FileSize": 69429529,
          "isStored": 0,
          "updateTime": "2015-06-10",
          "createTime": 1433896436000,
          "clockId": "",
          "duration": 1735000,
          "originalDuration": 1743166,
          "mp3Duration": 1735000,
          "listenNum": 75482,
          "likedNum": 37,
          "islistened": 0,
          "hasCopyright": 1,
          "type": 1,
          "tips": "",
          "commentNum": 2,
          "uploaderId": 2102332,
          "uploaderName": "凯叔讲故事",
          "uploaderImg": "http://img.kaolafm.net/mz/images/201511/52fd524c-7ca3-4158-8d37-c532eac187ee/default.jpg",
          "isReward": 0,
          "trailerStart": 0,
          "trailerEnd": 0
        },
        {
          "audioId": 1000001078288,
          "audioName": "【凯叔睡前诗】浪淘沙",
          "audioPic": "http://img.kaolafm.net/mz/images/201505/4c4bade5-a248-4736-a29c-aaa2589ccd04/default.jpg",
          "audioDes": "优质儿童故事自媒体平台。由著名主持人，两个女儿的父亲光头王凯创立。两天一次优质儿童绘本故事推送，每天一篇经典育儿文章推荐，更多互动活动为宝贝提供展示平台，帮助宝贝塑造健康的人格，和孩子一起成长。",
          "albumId": 1100000050295,
          "albumPic": "http://img.kaolafm.net/mz/images/201603/00553b48-49cd-4188-acf0-b979610214d4/default.png",
          "albumName": "凯叔讲故事",
          "orderNum": 7,
          "playUrl": "http://image.kaolafm.net/mz/outopus_16/201506/4f535e0e-4a3b-42ec-a3f6-8e9e60167b36.opus",
          "mp3PlayUrl": "http://image.kaolafm.net/mz/audios/201506/4f535e0e-4a3b-42ec-a3f6-8e9e60167b36.mp3",
          "aacPlayUrl": "http://image.kaolafm.net/mz/aac_64/201506/4f535e0e-4a3b-42ec-a3f6-8e9e60167b36.aac",
          "m3u8PlayUrl": "http://image.kaolafm.net/mz/aac_64/201506/4f535e0e-4a3b-42ec-a3f6-8e9e60167b36/playlist.m3u8",
          "shareUrl": "http://m.kaolafm.com/share/jm.html?audioId=1000001078288",
          "categoryId": 125,
          "host": [],
          "fileSize": 1398058,
          "aacFileSize": 1398058,
          "mp3FileSize": 6990922,
          "isStored": 0,
          "updateTime": "2015-06-10",
          "createTime": 1433896438000,
          "clockId": "",
          "duration": 174696,
          "originalDuration": 174744,
          "mp3Duration": 174744,
          "listenNum": 60750,
          "likedNum": 10,
          "islistened": 0,
          "hasCopyright": 1,
          "type": 1,
          "tips": "",
          "commentNum": 1,
          "uploaderId": 2102332,
          "uploaderName": "凯叔讲故事",
          "uploaderImg": "http://img.kaolafm.net/mz/images/201511/52fd524c-7ca3-4158-8d37-c532eac187ee/default.jpg",
          "isReward": 0,
          "trailerStart": 0,
          "trailerEnd": 0
        },
        {
          "audioId": 1000001078289,
          "audioName": "【凯叔讲故事】274. 达芬奇想飞（上）",
          "audioPic": "http://img.kaolafm.net/mz/images/201505/4c4bade5-a248-4736-a29c-aaa2589ccd04/default.jpg",
          "audioDes": "优质儿童故事自媒体平台。由著名主持人，两个女儿的父亲光头王凯创立。两天一次优质儿童绘本故事推送，每天一篇经典育儿文章推荐，更多互动活动为宝贝提供展示平台，帮助宝贝塑造健康的人格，和孩子一起成长。",
          "albumId": 1100000050295,
          "albumPic": "http://img.kaolafm.net/mz/images/201603/00553b48-49cd-4188-acf0-b979610214d4/default.png",
          "albumName": "凯叔讲故事",
          "orderNum": 8,
          "playUrl": "http://image.kaolafm.net/mz/outopus_16/201506/75cd22de-0152-441d-bb6b-227e982ad610.opus",
          "mp3PlayUrl": "http://image.kaolafm.net/mz/audios/201506/75cd22de-0152-441d-bb6b-227e982ad610.mp3",
          "aacPlayUrl": "http://image.kaolafm.net/mz/aac_64/201506/75cd22de-0152-441d-bb6b-227e982ad610.aac",
          "m3u8PlayUrl": "http://image.kaolafm.net/mz/aac_64/201506/75cd22de-0152-441d-bb6b-227e982ad610/playlist.m3u8",
          "shareUrl": "http://m.kaolafm.com/share/jm.html?audioId=1000001078289",
          "categoryId": 125,
          "host": [],
          "fileSize": 5493119,
          "aacFileSize": 5455495,
          "mp3FileSize": 26876382,
          "isStored": 0,
          "updateTime": "2015-06-10",
          "createTime": 1433896441000,
          "clockId": "",
          "duration": 671000,
          "originalDuration": 680546,
          "mp3Duration": 671000,
          "listenNum": 64496,
          "likedNum": 21,
          "islistened": 0,
          "hasCopyright": 1,
          "type": 1,
          "tips": "",
          "commentNum": 1,
          "uploaderId": 2102332,
          "uploaderName": "凯叔讲故事",
          "uploaderImg": "http://img.kaolafm.net/mz/images/201511/52fd524c-7ca3-4158-8d37-c532eac187ee/default.jpg",
          "isReward": 0,
          "trailerStart": 0,
          "trailerEnd": 0
        },
        {
          "audioId": 1000001078290,
          "audioName": "【凯叔讲故事】275. 达芬奇想飞（下）",
          "audioPic": "http://img.kaolafm.net/mz/images/201505/4c4bade5-a248-4736-a29c-aaa2589ccd04/default.jpg",
          "audioDes": "优质儿童故事自媒体平台。由著名主持人，两个女儿的父亲光头王凯创立。两天一次优质儿童绘本故事推送，每天一篇经典育儿文章推荐，更多互动活动为宝贝提供展示平台，帮助宝贝塑造健康的人格，和孩子一起成长。",
          "albumId": 1100000050295,
          "albumPic": "http://img.kaolafm.net/mz/images/201603/00553b48-49cd-4188-acf0-b979610214d4/default.png",
          "albumName": "凯叔讲故事",
          "orderNum": 9,
          "playUrl": "http://image.kaolafm.net/mz/outopus_16/201506/be5132a2-39b4-4be8-9725-abd4bf1f7e86.opus",
          "mp3PlayUrl": "http://image.kaolafm.net/mz/audios/201506/be5132a2-39b4-4be8-9725-abd4bf1f7e86.mp3",
          "aacPlayUrl": "http://image.kaolafm.net/mz/aac_64/201506/be5132a2-39b4-4be8-9725-abd4bf1f7e86.aac",
          "m3u8PlayUrl": "http://image.kaolafm.net/mz/aac_64/201506/be5132a2-39b4-4be8-9725-abd4bf1f7e86/playlist.m3u8",
          "shareUrl": "http://m.kaolafm.com/share/jm.html?audioId=1000001078290",
          "categoryId": 125,
          "host": [],
          "fileSize": 2580065,
          "aacFileSize": 5160884,
          "mp3FileSize": 25474782,
          "isStored": 0,
          "updateTime": "2015-06-10",
          "createTime": 1433896443000,
          "clockId": "",
          "duration": 636912,
          "originalDuration": 647839,
          "mp3Duration": 647839,
          "listenNum": 59931,
          "likedNum": 18,
          "islistened": 0,
          "hasCopyright": 1,
          "type": 1,
          "tips": "",
          "commentNum": 1,
          "uploaderId": 2102332,
          "uploaderName": "凯叔讲故事",
          "uploaderImg": "http://img.kaolafm.net/mz/images/201511/52fd524c-7ca3-4158-8d37-c532eac187ee/default.jpg",
          "isReward": 0,
          "trailerStart": 0,
          "trailerEnd": 0
        },
        {
          "audioId": 1000001078291,
          "audioName": "【凯叔睡前诗】破阵乐",
          "audioPic": "http://img.kaolafm.net/mz/images/201505/4c4bade5-a248-4736-a29c-aaa2589ccd04/default.jpg",
          "audioDes": "优质儿童故事自媒体平台。由著名主持人，两个女儿的父亲光头王凯创立。两天一次优质儿童绘本故事推送，每天一篇经典育儿文章推荐，更多互动活动为宝贝提供展示平台，帮助宝贝塑造健康的人格，和孩子一起成长。",
          "albumId": 1100000050295,
          "albumPic": "http://img.kaolafm.net/mz/images/201603/00553b48-49cd-4188-acf0-b979610214d4/default.png",
          "albumName": "凯叔讲故事",
          "orderNum": 10,
          "playUrl": "http://image.kaolafm.net/mz/outopus_16/201506/c7f88010-3ad4-4ba9-9927-7e8dd24cfcf5.opus",
          "mp3PlayUrl": "http://image.kaolafm.net/mz/audios/201506/c7f88010-3ad4-4ba9-9927-7e8dd24cfcf5.mp3",
          "aacPlayUrl": "http://image.kaolafm.net/mz/aac_64/201506/c7f88010-3ad4-4ba9-9927-7e8dd24cfcf5.aac",
          "m3u8PlayUrl": "http://image.kaolafm.net/mz/aac_64/201506/c7f88010-3ad4-4ba9-9927-7e8dd24cfcf5/playlist.m3u8",
          "shareUrl": "http://m.kaolafm.com/share/jm.html?audioId=1000001078291",
          "categoryId": 125,
          "host": [],
          "fileSize": 1237324,
          "aacFileSize": 1237324,
          "mp3FileSize": 6186442,
          "isStored": 0,
          "updateTime": "2015-06-10",
          "createTime": 1433896446000,
          "clockId": "",
          "duration": 154608,
          "originalDuration": 154632,
          "mp3Duration": 154632,
          "listenNum": 55278,
          "likedNum": 7,
          "islistened": 0,
          "hasCopyright": 1,
          "type": 1,
          "tips": "",
          "commentNum": 1,
          "uploaderId": 2102332,
          "uploaderName": "凯叔讲故事",
          "uploaderImg": "http://img.kaolafm.net/mz/images/201511/52fd524c-7ca3-4158-8d37-c532eac187ee/default.jpg",
          "isReward": 0,
          "trailerStart": 0,
          "trailerEnd": 0
        },
        {
          "audioId": 1000001078292,
          "audioName": "【凯叔讲故事】276. 苏和的白马",
          "audioPic": "http://img.kaolafm.net/mz/images/201505/4c4bade5-a248-4736-a29c-aaa2589ccd04/default.jpg",
          "audioDes": "优质儿童故事自媒体平台。由著名主持人，两个女儿的父亲光头王凯创立。两天一次优质儿童绘本故事推送，每天一篇经典育儿文章推荐，更多互动活动为宝贝提供展示平台，帮助宝贝塑造健康的人格，和孩子一起成长。",
          "albumId": 1100000050295,
          "albumPic": "http://img.kaolafm.net/mz/images/201603/00553b48-49cd-4188-acf0-b979610214d4/default.png",
          "albumName": "凯叔讲故事",
          "orderNum": 11,
          "playUrl": "http://image.kaolafm.net/mz/outopus_16/201506/0f199fe3-1c92-4885-a228-65ebcfb657e8.opus",
          "mp3PlayUrl": "http://image.kaolafm.net/mz/audios/201506/0f199fe3-1c92-4885-a228-65ebcfb657e8.mp3",
          "aacPlayUrl": "http://image.kaolafm.net/mz/aac_64/201506/0f199fe3-1c92-4885-a228-65ebcfb657e8.aac",
          "m3u8PlayUrl": "http://image.kaolafm.net/mz/aac_64/201506/0f199fe3-1c92-4885-a228-65ebcfb657e8/playlist.m3u8",
          "shareUrl": "http://m.kaolafm.com/share/jm.html?audioId=1000001078292",
          "categoryId": 125,
          "host": [],
          "fileSize": 4578220,
          "aacFileSize": 9156950,
          "mp3FileSize": 45303573,
          "isStored": 0,
          "updateTime": "2015-06-10",
          "createTime": 1433896448000,
          "clockId": "",
          "duration": 1132632,
          "originalDuration": 1144650,
          "mp3Duration": 1144650,
          "listenNum": 59784,
          "likedNum": 23,
          "islistened": 0,
          "hasCopyright": 1,
          "type": 1,
          "tips": "",
          "commentNum": 4,
          "uploaderId": 2102332,
          "uploaderName": "凯叔讲故事",
          "uploaderImg": "http://img.kaolafm.net/mz/images/201511/52fd524c-7ca3-4158-8d37-c532eac187ee/default.jpg",
          "isReward": 0,
          "trailerStart": 0,
          "trailerEnd": 0
        },
        {
          "audioId": 1000001078295,
          "audioName": "【凯叔讲故事】278. 爱心树",
          "audioPic": "http://img.kaolafm.net/mz/images/201505/4c4bade5-a248-4736-a29c-aaa2589ccd04/default.jpg",
          "audioDes": "优质儿童故事自媒体平台。由著名主持人，两个女儿的父亲光头王凯创立。两天一次优质儿童绘本故事推送，每天一篇经典育儿文章推荐，更多互动活动为宝贝提供展示平台，帮助宝贝塑造健康的人格，和孩子一起成长。",
          "albumId": 1100000050295,
          "albumPic": "http://img.kaolafm.net/mz/images/201603/00553b48-49cd-4188-acf0-b979610214d4/default.png",
          "albumName": "凯叔讲故事",
          "orderNum": 12,
          "playUrl": "http://image.kaolafm.net/mz/outopus_16/201506/1041c2b3-87d7-4b25-8f84-bba5120b50c8.opus",
          "mp3PlayUrl": "http://image.kaolafm.net/mz/audios/201506/1041c2b3-87d7-4b25-8f84-bba5120b50c8.mp3",
          "aacPlayUrl": "http://image.kaolafm.net/mz/aac_64/201506/1041c2b3-87d7-4b25-8f84-bba5120b50c8.aac",
          "m3u8PlayUrl": "http://image.kaolafm.net/mz/aac_64/201506/1041c2b3-87d7-4b25-8f84-bba5120b50c8/playlist.m3u8",
          "shareUrl": "http://m.kaolafm.com/share/jm.html?audioId=1000001078295",
          "categoryId": 125,
          "host": [],
          "fileSize": 5598930,
          "aacFileSize": 5643585,
          "mp3FileSize": 27779863,
          "isStored": 0,
          "updateTime": "2015-06-10",
          "createTime": 1433897235000,
          "clockId": "",
          "duration": 694000,
          "originalDuration": 703131,
          "mp3Duration": 694000,
          "listenNum": 57364,
          "likedNum": 20,
          "islistened": 0,
          "hasCopyright": 1,
          "type": 1,
          "tips": "",
          "commentNum": 1,
          "uploaderId": 2102332,
          "uploaderName": "凯叔讲故事",
          "uploaderImg": "http://img.kaolafm.net/mz/images/201511/52fd524c-7ca3-4158-8d37-c532eac187ee/default.jpg",
          "isReward": 0,
          "trailerStart": 0,
          "trailerEnd": 0
        },
        {
          "audioId": 1000001078296,
          "audioName": "【凯叔讲故事】279. 小兔汤姆和大坏狼",
          "audioPic": "http://img.kaolafm.net/mz/images/201505/4c4bade5-a248-4736-a29c-aaa2589ccd04/default.jpg",
          "audioDes": "优质儿童故事自媒体平台。由著名主持人，两个女儿的父亲光头王凯创立。两天一次优质儿童绘本故事推送，每天一篇经典育儿文章推荐，更多互动活动为宝贝提供展示平台，帮助宝贝塑造健康的人格，和孩子一起成长。",
          "albumId": 1100000050295,
          "albumPic": "http://img.kaolafm.net/mz/images/201603/00553b48-49cd-4188-acf0-b979610214d4/default.png",
          "albumName": "凯叔讲故事",
          "orderNum": 13,
          "playUrl": "http://image.kaolafm.net/mz/outopus_16/201506/02c67ac2-8748-4241-9b26-56a9d31fea76.opus",
          "mp3PlayUrl": "http://image.kaolafm.net/mz/audios/201506/02c67ac2-8748-4241-9b26-56a9d31fea76.mp3",
          "aacPlayUrl": "http://image.kaolafm.net/mz/aac_64/201506/02c67ac2-8748-4241-9b26-56a9d31fea76.aac",
          "m3u8PlayUrl": "http://image.kaolafm.net/mz/aac_64/201506/02c67ac2-8748-4241-9b26-56a9d31fea76/playlist.m3u8",
          "shareUrl": "http://m.kaolafm.com/share/jm.html?audioId=1000001078296",
          "categoryId": 125,
          "host": [],
          "fileSize": 1960488,
          "aacFileSize": 3922188,
          "mp3FileSize": 19111404,
          "isStored": 0,
          "updateTime": "2015-06-10",
          "createTime": 1433897238000,
          "clockId": "",
          "duration": 477828,
          "originalDuration": 489844,
          "mp3Duration": 489844,
          "listenNum": 62372,
          "likedNum": 15,
          "islistened": 0,
          "hasCopyright": 1,
          "type": 1,
          "tips": "",
          "commentNum": 0,
          "uploaderId": 2102332,
          "uploaderName": "凯叔讲故事",
          "uploaderImg": "http://img.kaolafm.net/mz/images/201511/52fd524c-7ca3-4158-8d37-c532eac187ee/default.jpg",
          "isReward": 0,
          "trailerStart": 0,
          "trailerEnd": 0
        },
        {
          "audioId": 1000001078297,
          "audioName": "【凯叔睡前诗】淮上与友人别",
          "audioPic": "http://img.kaolafm.net/mz/images/201505/4c4bade5-a248-4736-a29c-aaa2589ccd04/default.jpg",
          "audioDes": "优质儿童故事自媒体平台。由著名主持人，两个女儿的父亲光头王凯创立。两天一次优质儿童绘本故事推送，每天一篇经典育儿文章推荐，更多互动活动为宝贝提供展示平台，帮助宝贝塑造健康的人格，和孩子一起成长。",
          "albumId": 1100000050295,
          "albumPic": "http://img.kaolafm.net/mz/images/201603/00553b48-49cd-4188-acf0-b979610214d4/default.png",
          "albumName": "凯叔讲故事",
          "orderNum": 14,
          "playUrl": "http://image.kaolafm.net/mz/outopus_16/201506/24b27bbb-0167-4c06-93f0-85cb2a9552f7.opus",
          "mp3PlayUrl": "http://image.kaolafm.net/mz/audios/201506/24b27bbb-0167-4c06-93f0-85cb2a9552f7.mp3",
          "aacPlayUrl": "http://image.kaolafm.net/mz/aac_64/201506/24b27bbb-0167-4c06-93f0-85cb2a9552f7.aac",
          "m3u8PlayUrl": "http://image.kaolafm.net/mz/aac_64/201506/24b27bbb-0167-4c06-93f0-85cb2a9552f7/playlist.m3u8",
          "shareUrl": "http://m.kaolafm.com/share/jm.html?audioId=1000001078297",
          "categoryId": 125,
          "host": [],
          "fileSize": 1356202,
          "aacFileSize": 1313439,
          "mp3FileSize": 6567571,
          "isStored": 0,
          "updateTime": "2015-06-10",
          "createTime": 1433897240000,
          "clockId": "",
          "duration": 164000,
          "originalDuration": 164160,
          "mp3Duration": 164160,
          "listenNum": 52006,
          "likedNum": 5,
          "islistened": 0,
          "hasCopyright": 1,
          "type": 1,
          "tips": "",
          "commentNum": 0,
          "uploaderId": 2102332,
          "uploaderName": "凯叔讲故事",
          "uploaderImg": "http://img.kaolafm.net/mz/images/201511/52fd524c-7ca3-4158-8d37-c532eac187ee/default.jpg",
          "isReward": 0,
          "trailerStart": 0,
          "trailerEnd": 0
        },
        {
          "audioId": 1000001078299,
          "audioName": "【凯叔讲故事】281. 月光下的小老头",
          "audioPic": "http://img.kaolafm.net/mz/images/201505/4c4bade5-a248-4736-a29c-aaa2589ccd04/default.jpg",
          "audioDes": "优质儿童故事自媒体平台。由著名主持人，两个女儿的父亲光头王凯创立。两天一次优质儿童绘本故事推送，每天一篇经典育儿文章推荐，更多互动活动为宝贝提供展示平台，帮助宝贝塑造健康的人格，和孩子一起成长。",
          "albumId": 1100000050295,
          "albumPic": "http://img.kaolafm.net/mz/images/201603/00553b48-49cd-4188-acf0-b979610214d4/default.png",
          "albumName": "凯叔讲故事",
          "orderNum": 16,
          "playUrl": "http://image.kaolafm.net/mz/outopus_16/201506/6c9b7860-4303-4063-a6d1-342eed9edb7c.opus",
          "mp3PlayUrl": "http://image.kaolafm.net/mz/audios/201506/6c9b7860-4303-4063-a6d1-342eed9edb7c.mp3",
          "aacPlayUrl": "http://image.kaolafm.net/mz/aac_64/201506/6c9b7860-4303-4063-a6d1-342eed9edb7c.aac",
          "m3u8PlayUrl": "http://image.kaolafm.net/mz/aac_64/201506/6c9b7860-4303-4063-a6d1-342eed9edb7c/playlist.m3u8",
          "shareUrl": "http://m.kaolafm.com/share/jm.html?audioId=1000001078299",
          "categoryId": 125,
          "host": [],
          "fileSize": 4996920,
          "aacFileSize": 4956765,
          "mp3FileSize": 24437246,
          "isStored": 0,
          "updateTime": "2015-06-10",
          "createTime": 1433897246000,
          "clockId": "",
          "duration": 610000,
          "originalDuration": 618359,
          "mp3Duration": 610000,
          "listenNum": 55796,
          "likedNum": 19,
          "islistened": 0,
          "hasCopyright": 1,
          "type": 1,
          "tips": "",
          "commentNum": 2,
          "uploaderId": 2102332,
          "uploaderName": "凯叔讲故事",
          "uploaderImg": "http://img.kaolafm.net/mz/images/201511/52fd524c-7ca3-4158-8d37-c532eac187ee/default.jpg",
          "isReward": 0,
          "trailerStart": 0,
          "trailerEnd": 0
        }
      ]
    },
    "serverTime": 1503027203109
  },
  "active_play": {
    "audioId": 1000001078282,
    "audioName": "【凯叔讲故事】268. 爱音乐的马克",
    "audioPic": "http://img.kaolafm.net/mz/images/201505/4c4bade5-a248-4736-a29c-aaa2589ccd04/default.jpg",
    "audioDes": "优质儿童故事自媒体平台。由著名主持人，两个女儿的父亲光头王凯创立。两天一次优质儿童绘本故事推送，每天一篇经典育儿文章推荐，更多互动活动为宝贝提供展示平台，帮助宝贝塑造健康的人格，和孩子一起成长。",
    "albumId": 1100000050295,
    "albumPic": "http://img.kaolafm.net/mz/images/201603/00553b48-49cd-4188-acf0-b979610214d4/default.png",
    "albumName": "凯叔讲故事",
    "orderNum": 1,
    "playUrl": "http://image.kaolafm.net/mz/outopus_16/201506/21406f5e-db80-491d-a891-571a6477b558.opus",
    "mp3PlayUrl": "http://image.kaolafm.net/mz/audios/201506/21406f5e-db80-491d-a891-571a6477b558.mp3",
    "aacPlayUrl": "http://image.kaolafm.net/mz/aac_64/201506/21406f5e-db80-491d-a891-571a6477b558.aac",
    "m3u8PlayUrl": "http://image.kaolafm.net/mz/aac_64/201506/21406f5e-db80-491d-a891-571a6477b558/playlist.m3u8",
    "shareUrl": "http://m.kaolafm.com/share/jm.html?audioId=1000001078282",
    "categoryId": 125,
    "host": [],
    "fileSize": 4708130,
    "aacFileSize": 4769421,
    "mp3FileSize": 23550125,
    "isStored": 0,
    "updateTime": "2015-06-10",
    "createTime": 1433896016000,
    "clockId": "",
    "duration": 588000,
    "originalDuration": 599721,
    "mp3Duration": 588000,
    "listenNum": 121069,
    "likedNum": 243,
    "islistened": 0,
    "hasCopyright": 1,
    "type": 1,
    "tips": "",
    "commentNum": 20,
    "uploaderId": 2102332,
    "uploaderName": "凯叔讲故事",
    "uploaderImg": "http://img.kaolafm.net/mz/images/201511/52fd524c-7ca3-4158-8d37-c532eac187ee/default.jpg",
    "isReward": 0,
    "trailerStart": 0,
    "trailerEnd": 0
  },
  "active_xq": {}
}